dbbasic_follows/__init__.py
dbbasic_follows/admin.py
dbbasic_follows/follows.py
dbbasic_follows/api/__init__.py
dbbasic_follows/api/follows/__init__.py
dbbasic_follows/api/follows/list.py
dbbasic_follows-0.1.0.dist-info/licenses/LICENSE
dbbasic_follows-0.1.0.dist-info/METADATA
dbbasic_follows-0.1.0.dist-info/WHEEL
dbbasic_follows-0.1.0.dist-info/top_level.txt
dbbasic_follows-0.1.0.dist-info/RECORD
