Metadata-Version: 2.4
Name: dbbasic-follows
Version: 0.1.0
Summary: Social graph module for DBBasic - manage follows, friends, and connection suggestions
Author-email: DBBasic Contributors <info@dbbasic.com>
License: MIT
Project-URL: Homepage, https://dbbasic.com
Project-URL: Documentation, https://github.com/askrobots/dbbasic-follows
Project-URL: Repository, https://github.com/askrobots/dbbasic-follows
Project-URL: Issues, https://github.com/askrobots/dbbasic-follows/issues
Keywords: dbbasic,social,follows,friends,social-graph,web,framework
Classifier: Development Status :: 3 - Alpha
Classifier: Intended Audience :: Developers
Classifier: License :: OSI Approved :: MIT License
Classifier: Programming Language :: Python :: 3
Classifier: Programming Language :: Python :: 3.10
Classifier: Programming Language :: Python :: 3.11
Classifier: Programming Language :: Python :: 3.12
Requires-Python: >=3.10
License-File: LICENSE
Requires-Dist: dbbasic-web>=0.1.10
Requires-Dist: dbbasic-tsv>=1.0.0
Requires-Dist: dbbasic-admin>=0.1.1
Requires-Dist: dbbasic-accounts>=0.1.0
Dynamic: license-file
